gstreamer_plugins-1.27.90.data/purelib/gstreamer_plugins/__init__.py
gstreamer_plugins-1.27.90.data/purelib/gstreamer_plugins/lib/gstreamer-1.0/gstaccurip.dll
gstreamer_plugins-1.27.90.data/purelib/gstreamer_plugins/lib/gstreamer-1.0/gstadaptivedemux2.dll
gstreamer_plugins-1.27.90.data/purelib/gstreamer_plugins/lib/gstreamer-1.0/gstadpcmdec.dll
gstreamer_plugins-1.27.90.data/purelib/gstreamer_plugins/lib/gstreamer-1.0/gstadpcmenc.dll
gstreamer_plugins-1.27.90.data/purelib/gstreamer_plugins/lib/gstreamer-1.0/gstaes.dll
gstreamer_plugins-1.27.90.data/purelib/gstreamer_plugins/lib/gstreamer-1.0/gstaiff.dll
gstreamer_plugins-1.27.90.data/purelib/gstreamer_plugins/lib/gstreamer-1.0/gstalaw.dll
gstreamer_plugins-1.27.90.data/purelib/gstreamer_plugins/lib/gstreamer-1.0/gstalpha.dll
gstreamer_plugins-1.27.90.data/purelib/gstreamer_plugins/lib/gstreamer-1.0/gstalphacolor.dll
gstreamer_plugins-1.27.90.data/purelib/gstreamer_plugins/lib/gstreamer-1.0/gstamfcodec.dll
gstreamer_plugins-1.27.90.data/purelib/gstreamer_plugins/lib/gstreamer-1.0/gstamrnb.dll
gstreamer_plugins-1.27.90.data/purelib/gstreamer_plugins/lib/gstreamer-1.0/gstamrwbdec.dll
gstreamer_plugins-1.27.90.data/purelib/gstreamer_plugins/lib/gstreamer-1.0/gstanalyticsoverlay.dll
gstreamer_plugins-1.27.90.data/purelib/gstreamer_plugins/lib/gstreamer-1.0/gstapetag.dll
gstreamer_plugins-1.27.90.data/purelib/gstreamer_plugins/lib/gstreamer-1.0/gstasio.dll
gstreamer_plugins-1.27.90.data/purelib/gstreamer_plugins/lib/gstreamer-1.0/gstassrender.dll
gstreamer_plugins-1.27.90.data/purelib/gstreamer_plugins/lib/gstreamer-1.0/gstaudiobuffersplit.dll
gstreamer_plugins-1.27.90.data/purelib/gstreamer_plugins/lib/gstreamer-1.0/gstaudiofx.dll
gstreamer_plugins-1.27.90.data/purelib/gstreamer_plugins/lib/gstreamer-1.0/gstaudiofxbad.dll
gstreamer_plugins-1.27.90.data/purelib/gstreamer_plugins/lib/gstreamer-1.0/gstaudiolatency.dll
gstreamer_plugins-1.27.90.data/purelib/gstreamer_plugins/lib/gstreamer-1.0/gstaudiomixmatrix.dll
gstreamer_plugins-1.27.90.dist-info/METADATA
gstreamer_plugins-1.27.90.dist-info/WHEEL
gstreamer_plugins-1.27.90.dist-info/top_level.txt
gstreamer_plugins-1.27.90.dist-info/RECORD
